grift/__init__.py
grift/config.py
grift/loaders.py
grift/property_types.py
grift/utils.py
grift/tests/__init__.py
grift/tests/sample_config.json
grift/tests/test_config.py
grift/tests/test_loaders.py
grift/tests/test_property_type.py
grift-0.7.1.dist-info/AUTHORS.md
grift-0.7.1.dist-info/LICENSE
grift-0.7.1.dist-info/METADATA
grift-0.7.1.dist-info/WHEEL
grift-0.7.1.dist-info/top_level.txt
grift-0.7.1.dist-info/RECORD
