Metadata-Version: 2.1
Name: grift
Version: 0.7.1
Summary: A clean approach to app configuration
Home-page: https://github.com/kensho-technologies/grift
Maintainer-email: grift-maintainer@kensho.com
License: UNKNOWN
Keywords: app config configuration schema python
Platform: UNKNOWN
Requires-Dist: schematics (==1.1.1)
Requires-Dist: requests (>=2.13.0)
Requires-Dist: six (<2,>=1.11.0)
